LibreView/LibreView.py
LibreView/__init__.py
LibreView/models/Connection.py
LibreView/models/Device.py
LibreView/models/GlucoseMeasurement.py
LibreView/models/Practice.py
LibreView/models/Sensor.py
LibreView/models/User.py
LibreView/models/__init__.py
LibreView/utils/API.py
LibreView/utils/__init__.py
libreview-0.2.6.dist-info/METADATA
libreview-0.2.6.dist-info/WHEEL
libreview-0.2.6.dist-info/RECORD
