Metadata-Version: 2.4
Name: LibreView
Version: 0.2.6
Summary: API interface for LibreView / LibreLinkUp glucose readings
Project-URL: Homepage, https://github.com/PTST/LibreView_Py
Project-URL: Bug Tracker, https://github.com/PTST/LibreView_Py/issues
Requires-Python: >=3.11
Requires-Dist: dataclass-wizard
Requires-Dist: requests
